django_notification_system/__init__.py
django_notification_system/admin.py
django_notification_system/apps.py
django_notification_system/exceptions.py
django_notification_system/urls.py
django_notification_system/management/__init__.py
django_notification_system/management/commands/__init__.py
django_notification_system/management/commands/create_email_target_user_records.py
django_notification_system/management/commands/process_notifications.py
django_notification_system/migrations/0001_initial.py
django_notification_system/migrations/0002_auto_20201201_1720.py
django_notification_system/migrations/__init__.py
django_notification_system/models/__init__.py
django_notification_system/models/abstract.py
django_notification_system/models/notification.py
django_notification_system/models/opt_out.py
django_notification_system/models/target.py
django_notification_system/models/target_user_record.py
django_notification_system/notification_creators/__init__.py
django_notification_system/notification_creators/email.py
django_notification_system/notification_creators/expo.py
django_notification_system/notification_creators/twilio.py
django_notification_system/notification_handlers/__init__.py
django_notification_system/notification_handlers/email.py
django_notification_system/notification_handlers/expo.py
django_notification_system/notification_handlers/twilio.py
django_notification_system/tests/__init__.py
django_notification_system/tests/mock_exponent_server_sdk.py
django_notification_system/tests/management/__init__.py
django_notification_system/tests/management/commands/__init__.py
django_notification_system/tests/management/commands/test_create_email_user_targets.py
django_notification_system/tests/management/commands/test_process_notifications.py
django_notification_system/tests/smtp_tests/__init__.py
django_notification_system/tests/smtp_tests/test_smtp_exceptions.py
django_notification_system/tests/utils/__init__.py
django_notification_system-1.5.3.dist-info/LICENSE
django_notification_system-1.5.3.dist-info/METADATA
django_notification_system-1.5.3.dist-info/WHEEL
django_notification_system-1.5.3.dist-info/top_level.txt
django_notification_system-1.5.3.dist-info/RECORD
